{
  "slug": "cyl-guimara-24-333-26",
  "name": "Guimara",
  "municipality": "Peranzanes",
  "province": "Leon",
  "region": "Castilla y León",
  "country": "ES",
  "state": "controlado",
  "level": 0,
  "type": "forestal",
  "hectares": 7,
  "coordinates": [
    -6.689493879341972,
    42.892474034586286
  ],
  "startedAt": "2026-07-12T20:40:00.000Z",
  "updatedAt": "2026-07-15T22:47:46.410Z",
  "resources": {
    "aerial": 7,
    "ground": 20,
    "personnel": 11,
    "aerialUnits": [
      {
        "kind": "aereo",
        "count": 7
      }
    ],
    "groundUnits": [
      {
        "kind": "brigada",
        "count": 15
      },
      {
        "kind": "autobomba",
        "count": 3
      },
      {
        "kind": "maquinaria",
        "count": 2
      }
    ]
  },
  "timeline": [
    {
      "at": "2026-07-15T16:54:00.000Z",
      "label": "Controlado",
      "state": "controlado"
    },
    {
      "at": "2026-07-13T06:02:00.000Z",
      "label": "Nivel máximo 1"
    },
    {
      "at": "2026-07-12T20:40:00.000Z",
      "label": "Declarado",
      "state": "activo"
    }
  ],
  "sources": [
    "jcyl"
  ],
  "perimeter": [
    [
      -6.6946064,
      42.889406
    ],
    [
      -6.6949485,
      42.8890948
    ],
    [
      -6.695098,
      42.888783
    ],
    [
      -6.695055,
      42.8884706
    ],
    [
      -6.6948195,
      42.8881576
    ],
    [
      -6.6943914,
      42.887844
    ],
    [
      -6.6939988,
      42.8876207
    ],
    [
      -6.6936415,
      42.8874877
    ],
    [
      -6.6933196,
      42.887445
    ],
    [
      -6.693033,
      42.8874927
    ],
    [
      -6.6927495,
      42.8875914
    ],
    [
      -6.6924688,
      42.8877412
    ],
    [
      -6.6921912,
      42.887942
    ],
    [
      -6.6919165,
      42.8881939
    ],
    [
      -6.691669,
      42.888467
    ],
    [
      -6.6914488,
      42.8887613
    ],
    [
      -6.6912558,
      42.8890769
    ],
    [
      -6.6910899,
      42.8894138
    ],
    [
      -6.6909658,
      42.8896835
    ],
    [
      -6.6908834,
      42.8898862
    ],
    [
      -6.6908427,
      42.8900218
    ],
    [
      -6.6908436,
      42.8900904
    ],
    [
      -6.6910474,
      42.8901218
    ],
    [
      -6.6914539,
      42.890116
    ],
    [
      -6.6920632,
      42.8900731
    ],
    [
      -6.6928752,
      42.889993
    ],
    [
      -6.6935698,
      42.8898551
    ],
    [
      -6.6941468,
      42.8896594
    ],
    [
      -6.6946064,
      42.889406
    ]
  ],
  "hectaresApprox": true
}
